weather/__init__.py
weather/observations.py
weather/place.py
weather/uv_index.py
weather_au/__init__.py
weather_au/api.py
weather_au/observations.py
weather_au/place.py
weather_au/summary.py
weather_au/uv_index.py
weather_au-0.0.7.dist-info/LICENSE
weather_au-0.0.7.dist-info/METADATA
weather_au-0.0.7.dist-info/WHEEL
weather_au-0.0.7.dist-info/top_level.txt
weather_au-0.0.7.dist-info/RECORD
