Metadata-Version: 2.1
Name: weather-au
Version: 0.0.7
Summary: Australian Weather Data (from bom.gov.au)
Home-page: https://github.com/tonyallan/weather-au
Author: Tony Allan
Author-email: tony@apms.com.au
License: UNKNOWN
Platform: UNKNOWN
Classifier: Programming Language :: Python :: 3 :: Only
Classifier: License :: OSI Approved :: GNU General Public License v3 (GPLv3)
Classifier: Operating System :: OS Independent
Classifier: Development Status :: 2 - Pre-Alpha
Classifier: Topic :: Software Development :: Libraries :: Python Modules
Requires-Python: >=3.6
